piclap/__init__.py
piclap/_listener.py
piclap/_processor.py
piclap/_settings.py
pi_clap-1.4.2.dist-info/LICENSE
pi_clap-1.4.2.dist-info/METADATA
pi_clap-1.4.2.dist-info/WHEEL
pi_clap-1.4.2.dist-info/top_level.txt
pi_clap-1.4.2.dist-info/RECORD
