Metadata-Version: 2.1
Name: pi-clap
Version: 1.4.2
Summary: A python package for clap detection
Home-page: https://pi-clap.nikz.in
Author: Nikhil John
Author-email: ceo@jwala.diamonds
License: MIT
Download-URL: https://github.com/nikhiljohn10/pi-clap
Platform: any
Classifier: Intended Audience :: Developers
Classifier: Environment :: Console
Classifier: Operating System :: OS Independent
Classifier: Programming Language :: Python
Classifier: Programming Language :: Python :: 3.6
Classifier: Programming Language :: Python :: 3.7
Classifier: Programming Language :: Python :: 3.8
Classifier: Topic :: Software Development
Classifier: Topic :: Software Development :: Libraries
Classifier: Topic :: Utilities
Classifier: License :: OSI Approved :: MIT License
Requires-Python: >=3.6
Requires-Dist: gpiozero (==1.5.1)
Requires-Dist: pyaudio (==0.2.11)
Requires-Dist: munch (==2.5.0)
